Computer-Organization/computer-organization-HW2/HW2_sample_tb/alu.v
module alu #(parameter DWIDTH = 32)
(
    input [3:0] op,         // Operation to perform
    input [DWIDTH-1:0] rs1, // Input data #1.
    input [DWIDTH-1:0] rs2, // Input data #2.

    output reg [DWIDTH-1:0] rd, // Result of computation.
    output reg zero,            // zero = 1 if rd is 0, 0 otherwise.
    output reg overflow         // overflow = 1 if overflow happens.
);

    always@(op or rs1 or rs2) begin
        // default value
        overflow = 0;
        zero = 0;

        case (op)
            // and operation
            4'b0000: rd = rs1 & rs2;

            // or operation
            4'b0001: rd = rs1 | rs2;

            // add operation
            4'b0010: 
            begin
                rd = rs1 + rs2;
                overflow = (rs1[31] == rs2[31]) && (rs1[31] != rd[31]);
            end

            // subtract operation
            4'b0110: 
            begin
                rd = rs1 - rs2;
                overflow = (rs1[31] != rs2[31]) && (rs1[31] != rd[31]);
            end

            // nor operation
            4'b1100: rd = ~(rs1 | rs2);

            // slt operation
            4'b0111: rd = ($signed(rs1) < $signed(rs2)) ? 32'h1 : 32'h0;

            // default: do nothing
            default: rd = 32'h0;
        endcase

        // check if rd is 0
        zero = (rd == 32'h0) ? 1 : 0;
    end

endmodule

Computer-Organization/computer-organization-HW4/reg_file.v
/*
 *    Author : Che-Yu Wu @ EISL
 *    Date   : 2022-03-30
 */

module reg_file #(parameter DWIDTH = 32)
(
    input                 clk,      // system clock
    input                 rst,      // system reset

    input  [4 : 0]        rs1_id,   // register ID of data #1
    input  [4 : 0]        rs2_id,   // register ID of data #2 (if any)

    input                 we,       // if (we) R[rdst_id] <= rdst
    input  [4 : 0]        rdst_id,  // destination register ID
    input  [DWIDTH-1 : 0] rdst,     // input to destination register

    output [DWIDTH-1 : 0] rs1,      // register operand #1
    output [DWIDTH-1 : 0] rs2       // register operand #2 (if any)
);

    reg [DWIDTH-1:0] R[0:31];

    assign rs1 = R[rs1_id];
    assign rs2 = R[rs2_id];

    integer i;

    always @(posedge clk) begin
        if (rst) begin
            for (i = 0; i < 32; i = i + 1)
                R[i] <= 0;
        end
        else if (we && rdst_id != 0) begin
            R[rdst_id] <= rdst;
        end
    end

endmodule

Computer Organization/computer-organization-HW2/HW2_sample_tb/decode.v
/*
 *    Author : Che-Yu Wu @ EISL
 *    Date   : 2022-03-30
 */

module decode #(parameter DWIDTH = 32)
(
    input [DWIDTH-1:0]  instr,   // Input instruction.

    output reg [3 : 0]      op,      // Operation code for the ALU.
    output reg              ssel,    // Select the signal for either the immediate value or rs2.

    output reg [DWIDTH-1:0] imm,     // The immediate value (if used).
    output reg [4 : 0]      rs1_id,  // register ID for rs.
    output reg [4 : 0]      rs2_id,  // register ID for rt (if used).
    output reg [4 : 0]      rdst_id // register ID for rd or rt (if used).
);

/***************************************************************************************
    ---------------------------------------------------------------------------------
    | R_type |    |   opcode   |   rs   |   rt   |   rd   |   shamt   |    funct    |
    ---------------------------------------------------------------------------------
    | I_type |    |   opcode   |   rs   |   rt   |             immediate            |
    ---------------------------------------------------------------------------------
    | J_type |    |   opcode   |                     address                        |
    ---------------------------------------------------------------------------------
                   31        26 25    21 20    16 15    11 10        6 5           0
 ***************************************************************************************/

    localparam [3:0] OP_AND = 4'b0000,
                     OP_OR  = 4'b0001,
                     OP_ADD = 4'b0010,
                     OP_SUB = 4'b0110,
                     OP_NOR = 4'b1100,
                     OP_SLT = 4'b0111,
                     OP_NOT_DEFINED = 4'b1111;

    always @(instr) begin

        // case handling using opcode
        case(instr[31:26])
            
            // R-type
            6'b000000: begin
                
                // handle funct
                case(instr[5:0])
                    
                    // add rd, rs, rt
                    6'b100000: begin
                        
                        op = OP_ADD;
                        ssel = 1'b1;
                        
                        imm = 32'b0; // not used
                        rs1_id = instr[25:21];
                        rs2_id = instr[20:16];
                        rdst_id = instr[15:11];

                    end

                    // sub rd, rs, rt
                    6'b100010: begin
                        
                        op = OP_SUB;
                        ssel = 1'b1;
                        
                        imm = 32'b0; // not used
                        rs1_id = instr[25:21];
                        rs2_id = instr[20:16];
                        rdst_id = instr[15:11];

                    end

                    // and rd, rs, rt
                    6'b100100: begin
                        
                        op = OP_AND;
                        ssel = 1'b1;
                        
                        imm = 32'b0; // not used
                        rs1_id = instr[25:21];
                        rs2_id = instr[20:16];
                        rdst_id = instr[15:11];

                    end

                    // or rd, rs, rt
                    6'b100101: begin
                        
                        op = OP_OR;
                        ssel = 1'b1;
                        
                        imm = 32'b0; // not used
                        rs1_id = instr[25:21];
                        rs2_id = instr[20:16];
                        rdst_id = instr[15:11];

                    end

                    // nor rd, rs, rt
                    6'b100111: begin
                        
                        op = OP_NOR;
                        ssel = 1'b1;
                        
                        imm = 32'b0; // not used
                        rs1_id = instr[25:21];
                        rs2_id = instr[20:16];
                        rdst_id = instr[15:11];

                    end

                    // slt rd, rs, rt
                    6'b101010: begin
                        
                        op = OP_SLT;
                        ssel = 1'b1;
                        
                        imm = 32'b0; // not used
                        rs1_id = instr[25:21];
                        rs2_id = instr[20:16];
                        rdst_id = instr[15:11];

                    end

                    // default, not defined
                    default: begin
                        
                        op = OP_NOT_DEFINED;
                        ssel = 1'b0;
                        
                        imm = 32'b0; // not used
                        rs1_id = 5'b0; // not used
                        rs2_id = 5'b0; // not used
                        rdst_id = 5'b0; // not used

                    end

                endcase

            end

            // I-type addi rt, rs, imm
            6'b001000: begin
                
                op = OP_ADD;
                ssel = 1'b0;

                imm = $signed(instr[15:0]);
                rs1_id = instr[25:21];
                rs2_id = 5'b0; // not used
                rdst_id = instr[20:16];

            end

            // I-type slti rt, rs, imm
            6'b001010: begin
                
                op = OP_SLT;
                ssel = 1'b0;

                imm = $signed(instr[15:0]);
                rs1_id = instr[25:21];
                rs2_id = 5'b0; // not used
                rdst_id = instr[20:16];

            end

            // default, not defined
            default: begin
                
                op = OP_NOT_DEFINED;
                ssel = 1'b0;
                
                imm = 32'b0; // not used
                rs1_id = 5'b0; // not used
                rs2_id = 5'b0; // not used
                rdst_id = 5'b0; // not used

            end

        endcase

    end

endmodule

1. Archived/Computer-Organization/computer-organization-HW2/HW2_sample_tb/decode_tb.v
/*
 *    Author : Che-Yu Wu @ EISL
 *    Date   : 2022-03-30
 */

`timescale 1ns/1ps

module decode_tb (
    input         clk,
    input         rst,
    output reg    finish
);

    localparam DWIDTH = 32;

    reg [DWIDTH-1:0]  instr;
    wire [3:0]        op;
    wire              ssel;
    wire [DWIDTH-1:0] imm;
    wire [4:0]        rs1_id;
    wire [4:0]        rs2_id;
    wire [4:0]        rdst_id;

    wire              we;
    wire [DWIDTH-1:0] rs2_reg_file_out;

    wire [DWIDTH-1:0] rd;
    wire [DWIDTH-1:0] rs1;
    wire [DWIDTH-1:0] rs2;
    wire              zero;
    wire              overflow;


    decode decode_inst (
        // input
        .instr(instr),

        // output  
        .op(op),
        .ssel(ssel),
        .imm(imm),
        .rs1_id(rs1_id),
        .rs2_id(rs2_id),
        .rdst_id(rdst_id)
    );
    reg_file reg_file_inst (
        // input
        .clk(clk),
        .rst(rst),

        .rs1_id(rs1_id),
        .rs2_id(rs2_id),

        .we(we),
        .rdst_id(rdst_id),
        .rdst(rd),

        // output 
        .rs1(rs1),
        .rs2(rs2_reg_file_out)
    );

    alu alu_inst (
        // input
        .op(op),
        .rs1(rs1),
        .rs2(rs2),

        // output
        .rd(rd),
        .zero(zero),
        .overflow(overflow)
    );
    
    assign we = 1;
    assign rs2 = (ssel)? rs2_reg_file_out: imm;


    reg [3:0] golden_op;
    reg golden_ssel;
    reg [DWIDTH-1:0] golden_imm;
    reg [4:0] golden_rs1_id;
    reg [4:0] golden_rs2_id;
    reg [4:0] golden_rdst_id;

    wire rt_dont_care = !golden_ssel;
    wire imm_dont_care = golden_ssel;

    reg [DWIDTH-1:0] golden_R[0:31];
    integer golden_reg;
    integer i, pat_num, pattern, tmp, reg_pattern;

    initial begin

        $display("HIHI I'm testbench of HW2 ^u^ <3");
        pat_num = 0;
        pattern = $fopen("input.txt", "r");
        reg_pattern = $fopen("reg_file.txt", "r");

        finish = 0;
    end

    // Feed input signals to design @ positive edge of clock
    always @(posedge clk) begin

        if ($feof(pattern)) begin
            finish <= 1;
        end else if (!rst) begin
            tmp = $fscanf(pattern, "%d %d %d %d %d %d %d\n", instr, golden_op, golden_ssel, golden_imm, golden_rs1_id, golden_rs2_id,
                          golden_rdst_id);
        end

    end

    always @(negedge clk) begin

        if (!rst) begin
            if ((op !== golden_op) || (ssel !== golden_ssel) || (imm !== golden_imm && !imm_dont_care) || (rs1_id !== golden_rs1_id) ||
                (rs2_id !== golden_rs2_id && !rt_dont_care) || (rdst_id !== golden_rdst_id)) begin
                $display("Fail Pattern %d", pat_num);
                $display("Your op      : %10d,  Golden op      : %10d", op, golden_op);
                $display("Your ssel    : %10d,  Golden ssel    : %10d", ssel, golden_ssel);
                $display("Your imm     : %10d,  Golden imm     : %10d", $signed(imm), $signed(golden_imm));
                $display("Your rs1_id  : %10d,  Golden rs1_id  : %10d", rs1_id, golden_rs1_id);
                $display("Your rs2_id  : %10d,  Golden rs2_id  : %10d", rs2_id, golden_rs2_id);
                $display("Your rdst_id : %10d,  Golden rdst_id : %10d", rdst_id, golden_rdst_id);
                $finish;
                $finish;
            end
            else begin
                $display("Pass Pattern %d", pat_num);
            end
            pat_num = pat_num + 1;
        end
    end

    always @(negedge clk) begin
        if (finish) begin
            //print_reg;
            check_reg;
        end
    end

    task print_reg; begin
        integer idx;
        for (idx = 0; idx < 32; idx = idx + 1) begin
            // $display("R[%2d] = %d", idx, $signed(reg_file_inst.R[idx]));
        end
    end endtask

    task check_reg; begin
        for (i = 0; i < 32; i = i + 1) begin
            tmp = $fscanf(reg_pattern, "%d", golden_reg);
            golden_R[i] = golden_reg;
            $write("Check reg[%2d] : ", i);
            if (golden_R[i] !== reg_file_inst.R[i]) begin
                $display("Failed");
                $display("Your reg : %10d, Golden reg : %10d", $signed(reg_file_inst.R[i]), $signed(golden_R[i]));
            end
            else
                $display("Pass");
        end
        
    end endtask
endmodule

Computer Organization/computer-organization-HW2/HW2_sample_tb/waveform.vcd
$version Generated by VerilatedVcd $end
$date Sun Apr  2 20:04:20 2023
 $end
$timescale  10s $end

 $scope module TOP $end
  $var wire  1 | clk $end
  $var wire  1 ~ finish $end
  $var wire  1 } rst $end
  $scope module decode_tb $end
   $var wire 32 #! DWIDTH [31:0] $end
   $var wire  1 | clk $end
   $var wire  1 ~ finish $end
   $var wire 32 X golden_R(0) [31:0] $end
   $var wire 32 Y golden_R(1) [31:0] $end
   $var wire 32 b golden_R(10) [31:0] $end
   $var wire 32 c golden_R(11) [31:0] $end
   $var wire 32 d golden_R(12) [31:0] $end
   $var wire 32 e golden_R(13) [31:0] $end
   $var wire 32 f golden_R(14) [31:0] $end
   $var wire 32 g golden_R(15) [31:0] $end
   $var wire 32 h golden_R(16) [31:0] $end
   $var wire 32 i golden_R(17) [31:0] $end
   $var wire 32 j golden_R(18) [31:0] $end
   $var wire 32 k golden_R(19) [31:0] $end
   $var wire 32 Z golden_R(2) [31:0] $end
   $var wire 32 l golden_R(20) [31:0] $end
   $var wire 32 m golden_R(21) [31:0] $end
   $var wire 32 n golden_R(22) [31:0] $end
   $var wire 32 o golden_R(23) [31:0] $end
   $var wire 32 p golden_R(24) [31:0] $end
   $var wire 32 q golden_R(25) [31:0] $end
   $var wire 32 r golden_R(26) [31:0] $end
   $var wire 32 s golden_R(27) [31:0] $end
   $var wire 32 t golden_R(28) [31:0] $end
   $var wire 32 u golden_R(29) [31:0] $end
   $var wire 32 [ golden_R(3) [31:0] $end
   $var wire 32 v golden_R(30) [31:0] $end
   $var wire 32 w golden_R(31) [31:0] $end
   $var wire 32 \ golden_R(4) [31:0] $end
   $var wire 32 ] golden_R(5) [31:0] $end
   $var wire 32 ^ golden_R(6) [31:0] $end
   $var wire 32 _ golden_R(7) [31:0] $end
   $var wire 32 ` golden_R(8) [31:0] $end
   $var wire 32 a golden_R(9) [31:0] $end
   $var wire 32 R golden_imm [31:0] $end
   $var wire  4 P golden_op [3:0] $end
   $var wire  5 U golden_rdst_id [4:0] $end
   $var wire 32 x golden_reg [31:0] $end
   $var wire  5 S golden_rs1_id [4:0] $end
   $var wire  5 T golden_rs2_id [4:0] $end
   $var wire  1 Q golden_ssel $end
   $var wire 32 y i [31:0] $end
   $var wire 32 F imm [31:0] $end
   $var wire  1 Q imm_dont_care $end
   $var wire 32 C instr [31:0] $end
   $var wire  4 D op [3:0] $end
   $var wire  1 O overflow $end
   $var wire 32 z pat_num [31:0] $end
   $var wire 32 W pattern [31:0] $end
   $var wire 32 K rd [31:0] $end
   $var wire  5 I rdst_id [4:0] $end
   $var wire 32 { reg_pattern [31:0] $end
   $var wire 32 L rs1 [31:0] $end
   $var wire  5 G rs1_id [4:0] $end
   $var wire 32 M rs2 [31:0] $end
   $var wire  5 H rs2_id [4:0] $end
   $var wire 32 J rs2_reg_file_out [31:0] $end
   $var wire  1 } rst $end
   $var wire  1 V rt_dont_care $end
   $var wire  1 E ssel $end
   $var wire 32 !! tmp [31:0] $end
   $var wire  1 $! we $end
   $var wire  1 N zero $end
   $scope module alu_inst $end
    $var wire 32 #! DWIDTH [31:0] $end
    $var wire  4 D op [3:0] $end
    $var wire  1 O overflow $end
    $var wire 32 K rd [31:0] $end
    $var wire 32 L rs1 [31:0] $end
    $var wire 32 M rs2 [31:0] $end
    $var wire  1 N zero $end
   $upscope $end
   $scope module decode_inst $end
    $var wire 32 #! DWIDTH [31:0] $end
    $var wire  4 '! OP_ADD [3:0] $end
    $var wire  4 %! OP_AND [3:0] $end
    $var wire  4 )! OP_NOR [3:0] $end
    $var wire  4 +! OP_NOT_DEFINED [3:0] $end
    $var wire  4 &! OP_OR [3:0] $end
    $var wire  4 *! OP_SLT [3:0] $end
    $var wire  4 (! OP_SUB [3:0] $end
    $var wire 32 F imm [31:0] $end
    $var wire 32 C instr [31:0] $end
    $var wire  4 D op [3:0] $end
    $var wire  5 I rdst_id [4:0] $end
    $var wire  5 G rs1_id [4:0] $end
    $var wire  5 H rs2_id [4:0] $end
    $var wire  1 E ssel $end
   $upscope $end
   $scope module reg_file_inst $end
    $var wire 32 #! DWIDTH [31:0] $end
    $var wire 32 # R(0) [31:0] $end
    $var wire 32 $ R(1) [31:0] $end
    $var wire 32 - R(10) [31:0] $end
    $var wire 32 . R(11) [31:0] $end
    $var wire 32 / R(12) [31:0] $end
    $var wire 32 0 R(13) [31:0] $end
    $var wire 32 1 R(14) [31:0] $end
    $var wire 32 2 R(15) [31:0] $end
    $var wire 32 3 R(16) [31:0] $end
    $var wire 32 4 R(17) [31:0] $end
    $var wire 32 5 R(18) [31:0] $end
    $var wire 32 6 R(19) [31:0] $end
    $var wire 32 % R(2) [31:0] $end
    $var wire 32 7 R(20) [31:0] $end
    $var wire 32 8 R(21) [31:0] $end
    $var wire 32 9 R(22) [31:0] $end
    $var wire 32 : R(23) [31:0] $end
    $var wire 32 ; R(24) [31:0] $end
    $var wire 32 < R(25) [31:0] $end
    $var wire 32 = R(26) [31:0] $end
    $var wire 32 > R(27) [31:0] $end
    $var wire 32 ? R(28) [31:0] $end
    $var wire 32 @ R(29) [31:0] $end
    $var wire 32 & R(3) [31:0] $end
    $var wire 32 A R(30) [31:0] $end
    $var wire 32 B R(31) [31:0] $end
    $var wire 32 ' R(4) [31:0] $end
    $var wire 32 ( R(5) [31:0] $end
    $var wire 32 ) R(6) [31:0] $end
    $var wire 32 * R(7) [31:0] $end
    $var wire 32 + R(8) [31:0] $end
    $var wire 32 , R(9) [31:0] $end
    $var wire  1 | clk $end
    $var wire 32 K rdst [31:0] $end
    $var wire  5 I rdst_id [4:0] $end
    $var wire 32 L rs1 [31:0] $end
    $var wire  5 G rs1_id [4:0] $end
    $var wire 32 J rs2 [31:0] $end
    $var wire  5 H rs2_id [4:0] $end
    $var wire  1 } rst $end
    $var wire  1 $! we $end
    $scope module unnamedblk1 $end
     $var wire 32 "! i [31:0] $end
    $upscope $end
   $upscope $end
  $upscope $end
 $upscope $end
$enddefinitions $end


#0
b00000000000000000000000000000000 #
b00000000000000000000000000000000 $
b00000000000000000000000000000000 %
b00000000000000000000000000000000 &
b00000000000000000000000000000000 '
b00000000000000000000000000000000 (
b00000000000000000000000000000000 )
b00000000000000000000000000000000 *
b00000000000000000000000000000000 +
b00000000000000000000000000000000 ,
b00000000000000000000000000000000 -
b00000000000000000000000000000000 .
b00000000000000000000000000000000 /
b00000000000000000000000000000000 0
b00000000000000000000000000000000 1
b00000000000000000000000000000000 2
b00000000000000000000000000000000 3
b00000000000000000000000000000000 4
b00000000000000000000000000000000 5
b00000000000000000000000000000000 6
b00000000000000000000000000000000 7
b00000000000000000000000000000000 8
b00000000000000000000000000000000 9
b00000000000000000000000000000000 :
b00000000000000000000000000000000 ;
b00000000000000000000000000000000 <
b00000000000000000000000000000000 =
b00000000000000000000000000000000 >
b00000000000000000000000000000000 ?
b00000000000000000000000000000000 @
b00000000000000000000000000000000 A
b00000000000000000000000000000000 B
b00000000000000000000000000000000 C
b1111 D
0E
b00000000000000000000000000000000 F
b00000 G
b00000 H
b00000 I
b00000000000000000000000000000000 J
b00000000000000000000000000000000 K
b00000000000000000000000000000000 L
b00000000000000000000000000000000 M
1N
0O
b0000 P
0Q
b00000000000000000000000000000000 R
b00000 S
b00000 T
b00000 U
1V
b10000000000000000000000000101100 W
b00000000000000000000000000000000 X
b00000000000000000000000000000000 Y
b00000000000000000000000000000000 Z
b00000000000000000000000000000000 [
b00000000000000000000000000000000 \
b00000000000000000000000000000000 ]
b00000000000000000000000000000000 ^
b00000000000000000000000000000000 _
b00000000000000000000000000000000 `
b00000000000000000000000000000000 a
b00000000000000000000000000000000 b
b00000000000000000000000000000000 c
b00000000000000000000000000000000 d
b00000000000000000000000000000000 e
b00000000000000000000000000000000 f
b00000000000000000000000000000000 g
b00000000000000000000000000000000 h
b00000000000000000000000000000000 i
b00000000000000000000000000000000 j
b00000000000000000000000000000000 k
b00000000000000000000000000000000 l
b00000000000000000000000000000000 m
b00000000000000000000000000000000 n
b00000000000000000000000000000000 o
b00000000000000000000000000000000 p
b00000000000000000000000000000000 q
b00000000000000000000000000000000 r
b00000000000000000000000000000000 s
b00000000000000000000000000000000 t
b00000000000000000000000000000000 u
b00000000000000000000000000000000 v
b00000000000000000000000000000000 w
b00000000000000000000000000000000 x
b00000000000000000000000000000000 y
b00000000000000000000000000000000 z
b10000000000000000000000000101011 {
0|
1}
0~
b00000000000000000000000000000000 !!
b00000000000000000000000000000000 "!
b00000000000000000000000000100000 #!
1$!
b0000 %!
b0001 &!
b0010 '!
b0110 (!
b1100 )!
b0111 *!
b1111 +!
#1
1|
#2
0|
#3
1|
#4
0|
#5
b00000000110101110010100000101010 C
b0111 D
1E
b00110 G
b10111 H
b00101 I
b0111 P
1Q
b00000000000000000010100000101010 R
b00110 S
b10111 T
b00101 U
0V
1|
0}
b00000000000000000000000000000111 !!
#6
b00000000000000000000000000000001 z
0|
#7
b00101000001010001110010100110111 C
0E
b11111111111111111110010100110111 F
b00001 G
b00000 H
b01000 I
b11111111111111111110010100110111 M
0Q
b11111111111111111110010100110111 R
b00001 S
b01000 T
b01000 U
1V
1|
#8
b00000000000000000000000000000010 z
0|
#9
b00101011001110011000011101010111 C
b11111111111111111000011101010111 F
b11001 G
b11001 I
b11111111111111111000011101010111 M
b11111111111111111000011101010111 R
b11001 S
b11001 T
b11001 U
1|
#10
b00000000000000000000000000000011 z
0|
#11
b00000011100110011110000000100010 C
b0110 D
1E
b00000000000000000000000000000000 F
b11100 G
b11001 H
b11100 I
b00000000000000000000000000000000 M
b0110 P
1Q
b11111111111111111110000000100010 R
b11100 S
b11100 U
0V
1|
#12
b00000000000000000000000000000100 z
0|
#13
b00000010101100011100100000101010 C
b0111 D
b10101 G
b10001 H
b11001 I
b0111 P
b11111111111111111100100000101010 R
b10101 S
b10001 T
b11001 U
1|
#14
b00000000000000000000000000000101 z
0|
#15
b00000011010011111000000000100100 C
b0000 D
b11010 G
b01111 H
b10000 I
b0000 P
b11111111111111111000000000100100 R
b11010 S
b01111 T
b10000 U
1|
#16
b00000000000000000000000000000110 z
0|
#17
b00100000001011010110000001001000 C
b0010 D
0E
b00000000000000000110000001001000 F
b00001 G
b00000 H
b01101 I
b00000000000000000110000001001000 K
b00000000000000000110000001001000 M
0N
b0010 P
0Q
b00000000000000000110000001001000 R
b00001 S
b01101 T
b01101 U
1V
1|
#18
b00000000000000000000000000000111 z
0|
#19
b00000000000000000110000001001000 0
b00000001110000101011100000100101 C
b0001 D
1E
b00000000000000000000000000000000 F
b01110 G
b00010 H
b10111 I
b00000000000000000000000000000000 K
b00000000000000000000000000000000 M
1N
b0001 P
1Q
b11111111111111111011100000100101 R
b01110 S
b00010 T
b10111 U
0V
1|
#20
b00000000000000000000000000001000 z
0|
#21
b00100001000111110011101011111111 C
b0010 D
0E
b00000000000000000011101011111111 F
b01000 G
b00000 H
b11111 I
b00000000000000000011101011111111 K
b00000000000000000011101011111111 M
0N
b0010 P
0Q
b00000000000000000011101011111111 R
b01000 S
b11111 T
b11111 U
1V
1|
#22
b00000000000000000000000000001001 z
0|
#23
b00000000000000000011101011111111 B
b00101011100000011010100110011100 C
b0111 D
b11111111111111111010100110011100 F
b11100 G
b00001 I
b00000000000000000000000000000000 K
b11111111111111111010100110011100 M
1N
b0111 P
b11111111111111111010100110011100 R
b11100 S
b00001 T
b00001 U
1|
#24
b00000000000000000000000000001010 z
0|
#25
1|
1~
#26
b00000000000000000110000001001000 e
b00000000000000000011101011111111 w
b00000000000000000011101011111111 x
b00000000000000000000000000100000 y
b00000000000000000000000000001011 z
0|
b00000000000000000000000000000001 !!
