Digital Design/MP3/Clock.v
`timescale 100ms/10ms

// input:
//     clr_: clear, active low
//     enb:  enable counting
//     clk:  clock, trigger counting
// output:
//     count: 4-bit BCD counter
//     TC: 1-bit terminal count, 1 when count = 9
module BCD_counter(count,TC,clr_, enb, clk) ;
output [3:0] count ;
output TC ;
reg [3:0] count ;
input clr_, enb, clk ;
reg TC ;

always @ (*)
	if(enb && count >= 9)
		TC = 1;
	else
		TC = 0;
always @ (posedge clk or negedge clr_) // combinational+sequential
	if (~clr_)
		count = 0 ;
	else if (enb)
		if (TC)
			count = 0;
		else
			count = count + 1;
endmodule

// input: 
//     clr_: clear, active low
//     enb:  enable counting
//     clk:  clock, trigger counting
// output:
//     count: 3-bit hex counter, max = 5
//     TC: 1-bit terminal count, 1 when count = 5
module Hex_counter(count,TC,clr_, enb, clk) ;
output [2:0] count ;
output TC ;
reg [2:0] count ;
input clr_, enb, clk ;
reg TC ;

always @ (*)
	if(enb && count >= 5)
		TC = 1;
	else
		TC = 0;	


always @ (posedge clk or negedge clr_) // combinational+sequential
	if (~clr_)
		count = 0 ;
	else if (enb)
		if (TC)
			count = 0;
		else
			count = count + 1 ;
endmodule


module Testfixture ;
wire Vdd = 1'b1;
reg clk, clr_;
wire [3:0] m0 ;
wire [2:0] m1 ;

BCD_counter M0 (m0,m0_tc,clr_, Vdd, clk) ;
Hex_counter M1 (m1,m1_tc,clr_, m0_tc, clk) ;

//Stimulus
initial
begin
	clk = 1'b0 ;
	repeat(160)
		#5 clk = ~clk ;
	$finish ;
end
	
initial
begin
  clr_ = 0;
  #6  clr_ = 1'b1;  
end

initial
begin
$dumpfile("Clock.vcd");
$dumpvars;
end

endmodule

Digital Design/MP3/Clock.vcd
$date
	Wed May 10 17:01:58 2023
$end
$version
	Icarus Verilog
$end
$timescale
	10ms
$end
$scope module Testfixture $end
$var wire 1 ! Vdd $end
$var wire 1 " m1_tc $end
$var wire 3 # m1 [2:0] $end
$var wire 1 $ m0_tc $end
$var wire 4 % m0 [3:0] $end
$var reg 1 & clk $end
$var reg 1 ' clr_ $end
$scope module M0 $end
$var wire 1 & clk $end
$var wire 1 ' clr_ $end
$var wire 1 ! enb $end
$var reg 1 $ TC $end
$var reg 4 ( count [3:0] $end
$upscope $end
$scope module M1 $end
$var wire 1 & clk $end
$var wire 1 ' clr_ $end
$var wire 1 $ enb $end
$var reg 1 " TC $end
$var reg 3 ) count [2:0] $end
$upscope $end
$upscope $end
$enddefinitions $end
#0
$dumpvars
b0 )
b0 (
0'
0&
b0 %
0$
b0 #
0"
1!
$end
#50
1&
#60
1'
#100
0&
#150
b1 %
b1 (
1&
#200
0&
#250
b10 %
b10 (
1&
#300
0&
#350
b11 %
b11 (
1&
#400
0&
#450
b100 %
b100 (
1&
#500
0&
#550
b101 %
b101 (
1&
#600
0&
#650
b110 %
b110 (
1&
#700
0&
#750
b111 %
b111 (
1&
#800
0&
#850
b1000 %
b1000 (
1&
#900
0&
#950
1$
b1001 %
b1001 (
1&
#1000
0&
#1050
0$
b1 #
b1 )
b0 %
b0 (
1&
#1100
0&
#1150
b1 %
b1 (
1&
#1200
0&
#1250
b10 %
b10 (
1&
#1300
0&
#1350
b11 %
b11 (
1&
#1400
0&
#1450
b100 %
b100 (
1&
#1500
0&
#1550
b101 %
b101 (
1&
#1600
0&
#1650
b110 %
b110 (
1&
#1700
0&
#1750
b111 %
b111 (
1&
#1800
0&
#1850
b1000 %
b1000 (
1&
#1900
0&
#1950
1$
b1001 %
b1001 (
1&
#2000
0&
#2050
0$
b10 #
b10 )
b0 %
b0 (
1&
#2100
0&
#2150
b1 %
b1 (
1&
#2200
0&
#2250
b10 %
b10 (
1&
#2300
0&
#2350
b11 %
b11 (
1&
#2400
0&
#2450
b100 %
b100 (
1&
#2500
0&
#2550
b101 %
b101 (
1&
#2600
0&
#2650
b110 %
b110 (
1&
#2700
0&
#2750
b111 %
b111 (
1&
#2800
0&
#2850
b1000 %
b1000 (
1&
#2900
0&
#2950
1$
b1001 %
b1001 (
1&
#3000
0&
#3050
0$
b11 #
b11 )
b0 %
b0 (
1&
#3100
0&
#3150
b1 %
b1 (
1&
#3200
0&
#3250
b10 %
b10 (
1&
#3300
0&
#3350
b11 %
b11 (
1&
#3400
0&
#3450
b100 %
b100 (
1&
#3500
0&
#3550
b101 %
b101 (
1&
#3600
0&
#3650
b110 %
b110 (
1&
#3700
0&
#3750
b111 %
b111 (
1&
#3800
0&
#3850
b1000 %
b1000 (
1&
#3900
0&
#3950
1$
b1001 %
b1001 (
1&
#4000
0&
#4050
0$
b100 #
b100 )
b0 %
b0 (
1&
#4100
0&
#4150
b1 %
b1 (
1&
#4200
0&
#4250
b10 %
b10 (
1&
#4300
0&
#4350
b11 %
b11 (
1&
#4400
0&
#4450
b100 %
b100 (
1&
#4500
0&
#4550
b101 %
b101 (
1&
#4600
0&
#4650
b110 %
b110 (
1&
#4700
0&
#4750
b111 %
b111 (
1&
#4800
0&
#4850
b1000 %
b1000 (
1&
#4900
0&
#4950
1$
b1001 %
b1001 (
1&
#5000
0&
#5050
0$
b101 #
b101 )
b0 %
b0 (
1&
#5100
0&
#5150
b1 %
b1 (
1&
#5200
0&
#5250
b10 %
b10 (
1&
#5300
0&
#5350
b11 %
b11 (
1&
#5400
0&
#5450
b100 %
b100 (
1&
#5500
0&
#5550
b101 %
b101 (
1&
#5600
0&
#5650
b110 %
b110 (
1&
#5700
0&
#5750
b111 %
b111 (
1&
#5800
0&
#5850
b1000 %
b1000 (
1&
#5900
0&
#5950
1"
1$
b1001 %
b1001 (
1&
#6000
0&
#6050
0"
0$
b0 #
b0 )
b0 %
b0 (
1&
#6100
0&
#6150
b1 %
b1 (
1&
#6200
0&
#6250
b10 %
b10 (
1&
#6300
0&
#6350
b11 %
b11 (
1&
#6400
0&
#6450
b100 %
b100 (
1&
#6500
0&
#6550
b101 %
b101 (
1&
#6600
0&
#6650
b110 %
b110 (
1&
#6700
0&
#6750
b111 %
b111 (
1&
#6800
0&
#6850
b1000 %
b1000 (
1&
#6900
0&
#6950
1$
b1001 %
b1001 (
1&
#7000
0&
#7050
0$
b1 #
b1 )
b0 %
b0 (
1&
#7100
0&
#7150
b1 %
b1 (
1&
#7200
0&
#7250
b10 %
b10 (
1&
#7300
0&
#7350
b11 %
b11 (
1&
#7400
0&
#7450
b100 %
b100 (
1&
#7500
0&
#7550
b101 %
b101 (
1&
#7600
0&
#7650
b110 %
b110 (
1&
#7700
0&
#7750
b111 %
b111 (
1&
#7800
0&
#7850
b1000 %
b1000 (
1&
#7900
0&
#7950
1$
b1001 %
b1001 (
1&
